{
  "seo": {
    "title": "Entra ID: 1-Hour Briefing",
    "description": "Tackle IAM challenges with expert advice to boost security, streamline access, and improve compliance with Entra ID.",
    "canonical": "entra-id-1-hour-briefing",
    "showBreadcrumb": true
  },
  "blocks": [
    {
      "finalBreadcrumb": "Entra-ID-1-Hour-Briefing",
      "_template": "breadcrumbs"
    },
    {
      "heading": "Entra ID: 1-Hour Briefing",
      "body": "Address identity and access management challenges and receive expert advice on how to enhance security, streamline access, and improve compliance using Entra ID.",
      "tabletTextAlignment": "Left",
      "accordionItems": [
        {
          "label": "Business Process Analysis ",
          "content": "We examine your existing processes and workflows to identify opportunities for automation and optimization using Power Platform.\n"
        },
        {
          "label": "Blueprint Creation ",
          "content": "We create a comprehensive blueprint for your Power Platform solution, detailing the architecture, required components, and Azure integration points.\n"
        },
        {
          "label": "Licensing and Product Recommendations",
          "content": "We offer guidance on the most cost-effective licensing options and best practices for governing your Power Platform environment.\n"
        },
        {
          "label": "Product Backlog Items with Effort/Time Estimates",
          "content": "We provide a feature list with effort estimates, allowing for accurate planning and budgeting, while accounting for potential timeframe changes based on project scope.\n"
        },
        {
          "label": "Implementation Roadmap",
          "content": "We design an in-depth plan that outlines the steps necessary for successful Power Platform adoption, considering your business objectives and timelines.\n"
        }
      ],
      "buttons": [
        {
          "buttonText": "Book a Free Initial Meeting",
          "leadCaptureFormOption": "bookingJotFormId",
          "colour": 0
        },
        {
          "buttonText": "Rules to Best Practices for Entre ID",
          "buttonLink": "https://www.ssw.com.au/rules/managing-microsoft-entra-id",
          "colour": 1
        }
      ],
      "mediaConfiguration": {
        "placement": "Right",
        "imageSource": "/images/AAA-Mike/EntreID.png",
        "imageHeight": 888,
        "imageWidth": 1332
      },
      "_template": "accordionBlock"
    },
    {
      "heading": "Trusted in Sydney, Melbourne, Brisbane, and Newcastle by",
      "tabletTextAlignment": "Center",
      "paused": false,
      "isWhiteImages": true,
      "logos": [
        {
          "logo": "/images/clientLogos/allianz1.png",
          "altText": "Allianz"
        },
        {
          "logo": "/images/clientLogos/Cisco1.png",
          "altText": "Cisco"
        },
        {
          "logo": "/images/clientLogos/Bupa1.png",
          "altText": "Bupa"
        },
        {
          "logo": "/images/clientLogos/CBA-Primary.png",
          "altText": "Commbank"
        },
        {
          "logo": "/images/Clients/Untitled-4.png",
          "altText": "Westpac"
        },
        {
          "logo": "/images/clientLogos/Toll_Group_logo.svg.png",
          "altText": "Toll"
        },
        {
          "logo": "/images/clientLogos/medibank.webp",
          "altText": "Medibank"
        },
        {
          "logo": "/images/clientLogos/event-logo-white.webp",
          "altText": "Event"
        },
        {
          "logo": "/images/clientLogos/SydneyUni.png",
          "altText": "Sydney University"
        },
        {
          "logo": "/images/clientLogos/LL_logo_0.png",
          "altText": "Lend Lease"
        },
        {
          "logo": "/images/clientLogos/Pfizer_logo.svg.png",
          "altText": "Pfizer"
        }
      ],
      "_template": "logoCarousel"
    },
    {
      "isStacked": false,
      "heading": "The SSW Specification Review: Your Blueprint for Software Success",
      "isH1": false,
      "body": "You wouldn't build a house without an architect's plan, so don't build software without a specification. We define the roadmap, mitigate risks, and provide accurate estimates before a single line of code is written.",
      "tabletTextAlignment": "Center",
      "cards": [
        {
          "guid": "38c99c",
          "image": "/images/AAA-Mike/Screenshot%202026-01-08%20at%209.26.14%E2%80%AFAM.png",
          "altText": "The Specification Review",
          "icon": "info",
          "heading": "The Specification Review",
          "description": "Understanding a complex system takes more than one meeting. We spend time gathering stakeholder requirements to create a detailed project roadmap, ensuring we understand the destination before we start the journey.",
          "embeddedButton": {
            "buttonText": "Rules to Better Spec Reviews",
            "buttonLink": "https://www.ssw.com.au/rules/rules-to-better-specification-reviews"
          }
        },
        {
          "guid": "2demk",
          "image": "/images/AAA-Mike/Screenshot%202026-01-08%20at%209.27.38%E2%80%AFAM.png",
          "altText": "Requirements Analysis",
          "icon": "info",
          "heading": "Requirements Analysis",
          "description": "We break down the technical landscape to define your architectural roadmap, integration plans, and deployment strategy. By identifying the MVP and potential risks early, we prevent costly bottlenecks later.",
          "embeddedButton": {
            "buttonText": "Rules: Gathering Accurate Information",
            "buttonLink": "https://www.ssw.com.au/rules/get-accurate-information"
          }
        },
        {
          "guid": "qno9cp",
          "image": "/images/AAA-Mike/Screenshot%202026-01-08%20at%209.27.47%E2%80%AFAM.png",
          "altText": "Product Backlog",
          "icon": "info",
          "heading": "Product Backlog",
          "description": "We translate your requirements into a tangible list of Product Backlog Items (PBIs). This includes setting priorities, mapping dependencies, and estimating the effort required to build the solution step-by-step.",
          "embeddedButton": {
            "buttonText": "Rule: Build a Backlog",
            "buttonLink": "https://www.ssw.com.au/rules/break-pbis"
          }
        },
        {
          "guid": "n1u82s",
          "image": "/images/AAA-Mike/Screenshot%202026-01-08%20at%209.27.57%E2%80%AFAM.png",
          "altText": "Ballpark Estimates",
          "icon": "info",
          "heading": "Ballpark Estimates",
          "description": "Budget clarity is essential. We provide realistic projections on the number of sprints, the size of the development team, and the estimated total cost, giving you the data you need to secure approval.",
          "embeddedButton": {
            "buttonText": "Rule: Providing Estimates",
            "buttonLink": "https://www.ssw.com.au/rules/spec-give-customers-a-ballpark"
          }
        },
        {
          "guid": "1s72o",
          "image": "/images/AAA-Mike/Screenshot%202026-01-08%20at%209.28.06%E2%80%AFAM.png",
          "altText": "From Wireframes to Product",
          "icon": "info",
          "heading": "From Wireframes to Product",
          "description": "Deep engagement ensures we solve the right problem. We move from rough wireframes to detailed UX designs and final development, keeping you in the loop until the \"Definition of Done\" is met.",
          "embeddedButton": {
            "buttonText": "Rule: Definition of Done",
            "buttonLink": "https://www.ssw.com.au/rules/definition-of-done"
          }
        }
      ],
      "_template": "cardCarousel"
    },
    {
      "topLabel": {
        "labelText": ""
      },
      "heading": "Speak to SSW about your next **Power platform** project",
      "isH1": false,
      "description": "",
      "tabletTextAlignment": "Center",
      "featureColumns": {
        "twoColumns": true,
        "features": [
          {
            "heading": "Microsoft Power BI",
            "description": "Guide decision making with stunning reports and real-time insights from across your organization.",
            "icon": "BiLineChart"
          },
          {
            "heading": "Microsoft Power Apps",
            "description": "Build and launch professional-grade apps and automate workflows without additional coding.",
            "icon": "BiChip"
          },
          {
            "heading": "Microsoft Power Automate",
            "description": "Boost productivity by automating repetitive tasks and workflows with process automation.",
            "icon": "BiArrowFromLeft"
          },
          {
            "heading": "Microsoft Power Pages",
            "description": "Create websites and customer solutions fast while securely storing and managing data. ",
            "icon": "BiAddToQueue"
          },
          {
            "heading": "Microsoft Copilot Studio",
            "description": "Transform customer and employee experiences when you build custom copilots.",
            "icon": "BiPaperPlane"
          }
        ]
      },
      "_template": "imageTextBlock"
    },
    {
      "buttonText": "Book a Free Initial Meeting",
      "animated": true,
      "buttonSubtitle": "or call +61 2 9953 3000",
      "_template": "BookingButton"
    }
  ],
  "azureBanner": {
    "azureFooterColor": "darkgray"
  }
}